{
  "info": {
    "name": "AI-Based Employee Performance Analytics - Examples",
    "description": "Sample requests for authentication, employees CRUD/search, and AI recommendations.",
    "schema": "https://schema.getpostman.com/json/collection/v2.1.0/collection.json"
  },
  "item": [
    {
      "name": "Signup",
      "request": {
        "method": "POST",
        "header": [
          {
            "key": "Content-Type",
            "value": "application/json"
          }
        ],
        "url": {
          "raw": "http://localhost:5000/api/auth/signup",
          "protocol": "http",
          "host": [
            "localhost"
          ],
          "port": "5000",
          "path": [
            "api",
            "auth",
            "signup"
          ]
        },
        "body": {
          "mode": "raw",
          "raw": "{\n  \"name\": \"HR Admin\",\n  \"email\": \"admin@example.com\",\n  \"password\": \"Password123!\"\n}"
        }
      }
    },
    {
      "name": "Login",
      "request": {
        "method": "POST",
        "header": [
          {
            "key": "Content-Type",
            "value": "application/json"
          }
        ],
        "url": {
          "raw": "http://localhost:5000/api/auth/login",
          "protocol": "http",
          "host": [
            "localhost"
          ],
          "port": "5000",
          "path": [
            "api",
            "auth",
            "login"
          ]
        },
        "body": {
          "mode": "raw",
          "raw": "{\n  \"email\": \"admin@example.com\",\n  \"password\": \"Password123!\"\n}"
        }
      }
    },
    {
      "name": "Create Employee",
      "request": {
        "method": "POST",
        "header": [
          {
            "key": "Content-Type",
            "value": "application/json"
          },
          {
            "key": "Authorization",
            "value": "Bearer {{jwt}}"
          }
        ],
        "url": {
          "raw": "http://localhost:5000/api/employees",
          "protocol": "http",
          "host": [
            "localhost"
          ],
          "port": "5000",
          "path": [
            "api",
            "employees"
          ]
        },
        "body": {
          "mode": "raw",
          "raw": "{\n  \"name\": \"John Doe\",\n  \"email\": \"john.doe@example.com\",\n  \"department\": \"Development\",\n  \"skills\": [\"React\", \"Node.js\"],\n  \"performanceScore\": 86,\n  \"experience\": 3\n}"
        }
      }
    },
    {
      "name": "Get Employees",
      "request": {
        "method": "GET",
        "header": [
          {
            "key": "Authorization",
            "value": "Bearer {{jwt}}"
          }
        ],
        "url": {
          "raw": "http://localhost:5000/api/employees",
          "protocol": "http",
          "host": [
            "localhost"
          ],
          "port": "5000",
          "path": [
            "api",
            "employees"
          ]
        }
      }
    },
    {
      "name": "Search by Department",
      "request": {
        "method": "GET",
        "header": [
          {
            "key": "Authorization",
            "value": "Bearer {{jwt}}"
          }
        ],
        "url": {
          "raw": "http://localhost:5000/api/employees/search?department=Development",
          "protocol": "http",
          "host": [
            "localhost"
          ],
          "port": "5000",
          "path": [
            "api",
            "employees",
            "search"
          ],
          "query": [
            {
              "key": "department",
              "value": "Development"
            }
          ]
        }
      }
    },
    {
      "name": "AI Recommend (Promotion/Ranking/Training/Feedback)",
      "request": {
        "method": "POST",
        "header": [
          {
            "key": "Content-Type",
            "value": "application/json"
          },
          {
            "key": "Authorization",
            "value": "Bearer {{jwt}}"
          }
        ],
        "url": {
          "raw": "http://localhost:5000/api/ai/recommend",
          "protocol": "http",
          "host": [
            "localhost"
          ],
          "port": "5000",
          "path": [
            "api",
            "ai",
            "recommend"
          ]
        },
        "body": {
          "mode": "raw",
          "raw": "{\n  \"mode\": \"promotion\",\n  \"department\": \"Development\"\n}"
        }
      }
    }
  ]
}

